GHIElectronics/__init__.py
GHIElectronics/Endpoint/__init__.py
GHIElectronics/Endpoint/Core/__init__.py
GHIElectronics/Endpoint/Core/EPM815/Adc.py
GHIElectronics/Endpoint/Core/EPM815/Display.py
GHIElectronics/Endpoint/Core/EPM815/Gpio.py
GHIElectronics/Endpoint/Core/EPM815/I2c.py
GHIElectronics/Endpoint/Core/EPM815/Pwm.py
GHIElectronics/Endpoint/Core/EPM815/Register.py
GHIElectronics/Endpoint/Core/EPM815/Rtc.py
GHIElectronics/Endpoint/Core/EPM815/SerialPort.py
GHIElectronics/Endpoint/Core/EPM815/Spi.py
GHIElectronics/Endpoint/Core/EPM815/__init__.py
GHIElectronics.Endpoint.Core-0.1.3.dist-info/METADATA
GHIElectronics.Endpoint.Core-0.1.3.dist-info/WHEEL
GHIElectronics.Endpoint.Core-0.1.3.dist-info/top_level.txt
GHIElectronics.Endpoint.Core-0.1.3.dist-info/RECORD
