Metadata-Version: 2.1
Name: GHIElectronics.Endpoint.Core
Version: 0.1.3
Summary: GHI Electronics Endpoint Python library.
Home-page: https://www.ghielectronics.com/
Author: GHI Electronics
Author-email: support@ghielectronics.com
License: MIT
Classifier: Programming Language :: Python :: 3
Requires-Python: >=3.10
